google_nest_camera_proxy/__init__.py
google_nest_camera_proxy/__main__.py
google_nest_camera_proxy/auth.py
google_nest_camera_proxy/camera.py
google_nest_camera_proxy/google_nest_camera_proxy.py
google_nest_camera_proxy/rtsp_server.py
google_nest_camera_proxy-1.1.0.dist-info/LICENSE
google_nest_camera_proxy-1.1.0.dist-info/METADATA
google_nest_camera_proxy-1.1.0.dist-info/WHEEL
google_nest_camera_proxy-1.1.0.dist-info/entry_points.txt
google_nest_camera_proxy-1.1.0.dist-info/RECORD
