Metadata-Version: 2.1
Name: google-nest-camera-proxy
Version: 1.1.0
Summary: Proxy your Nest Camera through rtsp-simple-server so you can view it on any RTSP reader
License: MIT
Author: Xev Gittler
Requires-Python: >=3.9,<4.0
Classifier: License :: OSI Approved :: MIT License
Classifier: Programming Language :: Python :: 3
Classifier: Programming Language :: Python :: 3.9
Classifier: Programming Language :: Python :: 3.10
Classifier: Programming Language :: Python :: 3.11
Requires-Dist: click (>=8.1.6,<9.0.0)
Requires-Dist: colorama (>=0.4.6,<0.5.0)
Requires-Dist: configparser (>=6.0.0,<7.0.0)
Requires-Dist: python-dateutil (>=2.8.2,<3.0.0)
Requires-Dist: python-google-nest (>=5.1.1,<6.0.0)
Project-URL: Homepage, https://github.com/xevg/google-nest-camera-proxy
